modelta/Pvalue.py
modelta/ReadFile.py
modelta/__init__.py
modelta/__version__.py
modelta/auxi.py
modelta/mDELTA.py
modelta/mymath.py
modelta/mytest.py
modelta-1.0.30.dist-info/LICENSE
modelta-1.0.30.dist-info/METADATA
modelta-1.0.30.dist-info/WHEEL
modelta-1.0.30.dist-info/top_level.txt
modelta-1.0.30.dist-info/RECORD
