Metadata-Version: 2.1
Name: modelta
Version: 1.0.30
Summary: Chen and Yang Lab Multi fork Development cell lineage tree alignment 
Home-page: https://github.com/Chenjy0212/modelta
Author: EeWhile(Jingyu Chen)
Author-email: 1026224216@qq.com
License: MIT
Classifier: License :: OSI Approved :: MIT License
Classifier: Programming Language :: Python
Classifier: Programming Language :: Python :: 3
Classifier: Programming Language :: Python :: 3.6
Classifier: Programming Language :: Python :: Implementation :: CPython
Classifier: Programming Language :: Python :: Implementation :: PyPy
Requires-Python: >=3.6.0
License-File: LICENSE
Requires-Dist: pandas
Requires-Dist: tqdm
Requires-Dist: numpy
Requires-Dist: munkres
